duck/Constants.py
duck/__init__.py
duck/__main__.py
deduck-1.0.2.dist-info/METADATA
deduck-1.0.2.dist-info/WHEEL
deduck-1.0.2.dist-info/top_level.txt
deduck-1.0.2.dist-info/RECORD
