Metadata-Version: 2.1
Name: deduck
Version: 1.0.2
Summary: Hi! explain your problem to me... quack! quack!
Home-page: https://github.com/ArticOff/info
Author: Artic#3065
Author-email: artic.admisoffi@gmail.com
Maintainer: Artic#3065
Maintainer-email: artic.admisoffi@gmail.com
License: MIT
Project-URL: Source, https://github.com/ArticOff/deduck
Project-URL: Discord, https://articoff.github.io/discord
Project-URL: Tracker, https://github.com/ArticOff/deduck/issues
Platform: UNKNOWN
Classifier: Development Status :: 5 - Production/Stable
Classifier: License :: OSI Approved :: MIT License
Classifier: Intended Audience :: Developers
Classifier: Natural Language :: English
Classifier: Programming Language :: Python :: 3
Classifier: Programming Language :: Python
Classifier: Environment :: Console
Classifier: Environment :: Win32 (MS Windows)
Classifier: Framework :: Pytest
Classifier: Operating System :: OS Independent
Requires-Dist: requests
